<?xml version="1.0"?>
<?xml-stylesheet type="text/xsl" href="http://jsbsim.sourceforge.net/JSBSim.xsl"?>

<!-- Eurofighter Typhoon Aerodynamics -->
<!-- Justin Nicholson (pinto), Joshua Davidson (it0uchpods) -->

<aerodynamics>
	
	<axis name="LIFT">
		
		<!-- Lift above 0.85 and below -0.85 is generalised -->
		<function name="aero/force/Lift_alpha">
			<description>Lift due to alpha</description>
			<product>
				<property>aero/qbar-psf</property>
				<property>metrics/Sw-sqft</property>
				<table>
					<independentVar lookup="row">aero/alpha-deg</independentVar>
					<tableData>
						-50 -1.00
						  0  0.09
						 15  0.75
						 35  1.23
						 40  0.70
						 50  1.03
						 90  0.00
					</tableData>
				</table>
				<property>tune/lift/alpha</property>
			</product>
		</function>
		
		<function name="aero/force/Lift_pitch_rate">
			<description>Lift due to pitch rate</description>
			<product>
				<property>aero/qbar-psf</property>
				<property>metrics/Sw-sqft</property>
				<property>velocities/q-aero-rad_sec</property>
				<property>aero/ci2vel</property>
				<value>0.3888</value>
				<property>tune/lift/pitch_rate</property>
			</product>
		</function>
		
		<function name="aero/force/Lift_alpha_rate">
			<description>Lift due to alpha rate</description>
			<product>
				<property>aero/qbar-psf</property>
				<property>metrics/Sw-sqft</property>
				<property>aero/alphadot-rad_sec</property>
				<property>aero/ci2vel</property>
				<value>0.3699</value>
				<property>tune/lift/alpha_rate</property>
			</product>
		</function>
		
		<function name="aero/force/Lift_foreplane_L">
			<description>Lift due to foreplane L deflection</description>
			<product>
				<property>aero/qbar-psf</property>
				<property>metrics/Sw-sqft</property>
				<toradians><property>fcs/foreplane-L-deg</property></toradians>
				<value>0.0893</value>
			</product>
		</function>
		
		<function name="aero/force/Lift_foreplane_R">
			<description>Lift due to foreplane R deflection</description>
			<product>
				<property>aero/qbar-psf</property>
				<property>metrics/Sw-sqft</property>
				<toradians><property>fcs/foreplane-R-deg</property></toradians>
				<value>0.0893</value>
			</product>
		</function>
		
		<function name="aero/force/Lift_elevon_1L">
			<description>Lift due to elevon 1L deflection</description>
			<product>
				<property>aero/qbar-psf</property>
				<property>metrics/Sw-sqft</property>
				<toradians><property>fcs/elevon-1L-deg</property></toradians>
				<value>0.0883</value>
			</product>
		</function>
		
		<function name="aero/force/Lift_elevon_2L">
			<description>Lift due to elevon 2L deflection</description>
			<product>
				<property>aero/qbar-psf</property>
				<property>metrics/Sw-sqft</property>
				<toradians><property>fcs/elevon-2L-deg</property></toradians>
				<value>0.0903</value>
			</product>
		</function>
		
		<function name="aero/force/Lift_elevon_2R">
			<description>Lift due to elevon 2R deflection</description>
			<product>
				<property>aero/qbar-psf</property>
				<property>metrics/Sw-sqft</property>
				<toradians><property>fcs/elevon-2R-deg</property></toradians>
				<value>0.0903</value>
			</product>
		</function>
		
		<function name="aero/force/Lift_elevon_1R">
			<description>Lift due to elevon 1R deflection</description>
			<product>
				<property>aero/qbar-psf</property>
				<property>metrics/Sw-sqft</property>
				<toradians><property>fcs/elevon-1R-deg</property></toradians>
				<value>0.0883</value>
			</product>
		</function>
		
		<function name="aero/force/Lift_slat_L">
			<description>Delta Lift due to slat L</description>
			<product>
				<property>aero/qbar-psf</property>
				<property>metrics/Sw-sqft</property>
				<property>fcs/slat-L-deg</property>
				<value>0.00498</value>
			</product>
		</function>
		
		<function name="aero/force/Lift_slat_R">
			<description>Delta Lift due to slat R</description>
			<product>
				<property>aero/qbar-psf</property>
				<property>metrics/Sw-sqft</property>
				<property>fcs/slat-R-deg</property>
				<value>0.00498</value>
			</product>
		</function>
		
		<function name="aero/force/Lift_airbrake">
			<description>Delta Lift due to airbrake</description>
			<product>
				<property>aero/qbar-psf</property>
				<property>metrics/Sw-sqft</property>
				<property>fcs/airbrake-deg</property>
				<value>-0.000986</value>
			</product>
		</function>
	
	</axis>
	
	<axis name="DRAG">
		
		<!-- CD0 is based on fuselage, wing, horizontal- en vertical tail -->
		<!-- Antennas, struts and wires are not taken into account        -->
		<!-- CD for gear (fixed and retractable) is defined below         -->
		<function name="aero/force/Drag_minimum">
			<description>Minimum drag</description>
			<product>
				<property>aero/qbar-psf</property>
				<property>metrics/Sw-sqft</property>
				<value>0.0268</value>
				<property>tune/drag/minimum</property>
			</product>
		</function>
		
		<function name="aero/force/Drag_alpha">
			<description>Drag due to alpha</description>
			<product>
				<property>aero/qbar-psf</property>
				<property>metrics/Sw-sqft</property>
				<table>
					<independentVar lookup="row">aero/alpha-rad</independentVar>
					<tableData>
						-12.55  11.3242
						 -1.57   1.4085
						  0.00   0.0000
						  1.57   1.4085
						 12.55  11.3242
					</tableData>
				</table>
				<property>tune/drag/alpha</property>
			</product>
		</function>
		
		<function name="aero/force/Drag_induced">
			<description>Induced drag</description>
			<product>
				<property>aero/qbar-psf</property>
				<property>metrics/Sw-sqft</property>
				<property>aero/cl-squared</property>
				<value>0.063461</value>
				<property>tune/drag/induced</property>
			</product>
		</function>
		
		<function name="aero/force/Drag_mach">
			<description>Drag due to mach</description>
			<product>
				<property>aero/qbar-psf</property>
				<property>metrics/Sw-sqft</property>
				<table>
					<independentVar lookup="row">velocities/mach</independentVar>
					<tableData>
						0.00  0.000
						0.81  0.000
						1.10  0.023
						1.80  0.015
					</tableData>
				</table>
				<property>tune/drag/mach</property>
			</product>
		</function>
		
		<function name="aero/force/Drag_beta">
			<description>Drag due to sideslip</description>
			<product>
				<property>aero/qbar-psf</property>
				<property>metrics/Sw-sqft</property>
				<table>
					<independentVar lookup="row">aero/beta-rad</independentVar>
					<tableData>
						-1.57  1.23
						-0.26  0.05
						 0.00  0.00
						 0.26  0.05
						 1.57  1.23
					</tableData>
				</table>
				<property>tune/drag/beta</property>
			</product>
		</function>
		
		<function name="aero/force/Drag_foreplane_L">
			<description>Drag due to foreplane L deflection</description>
			<product>
				<property>aero/qbar-psf</property>
				<property>metrics/Sw-sqft</property>
				<abs><toradians><property>fcs/foreplane-L-deg</property></toradians></abs>
				<value>0.007</value>
			</product>
		</function>
		
		<function name="aero/force/Drag_foreplane_R">
			<description>Drag due to foreplane R deflection</description>
			<product>
				<property>aero/qbar-psf</property>
				<property>metrics/Sw-sqft</property>
				<abs><toradians><property>fcs/foreplane-R-deg</property></toradians></abs>
				<value>0.007</value>
			</product>
		</function>
		
		<function name="aero/force/Drag_elevon_1L">
			<description>Drag due to elevon 1L deflection</description>
			<product>
				<property>aero/qbar-psf</property>
				<property>metrics/Sw-sqft</property>
				<abs><toradians><property>fcs/elevon-1L-deg</property></toradians></abs>
				<value>0.005</value>
			</product>
		</function>
		
		<function name="aero/force/Drag_elevon_2L">
			<description>Drag due to elevon 2L deflection</description>
			<product>
				<property>aero/qbar-psf</property>
				<property>metrics/Sw-sqft</property>
				<abs><toradians><property>fcs/elevon-2L-deg</property></toradians></abs>
				<value>0.007</value>
			</product>
		</function>
		
		<function name="aero/force/Drag_elevon_2R">
			<description>Drag due to elevon 2R deflection</description>
			<product>
				<property>aero/qbar-psf</property>
				<property>metrics/Sw-sqft</property>
				<abs><toradians><property>fcs/elevon-2R-deg</property></toradians></abs>
				<value>0.007</value>
			</product>
		</function>
		
		<function name="aero/force/Drag_elevon_1R">
			<description>Drag due to elevon 1R deflection</description>
			<product>
				<property>aero/qbar-psf</property>
				<property>metrics/Sw-sqft</property>
				<abs><toradians><property>fcs/elevon-1R-deg</property></toradians></abs>
				<value>0.005</value>
			</product>
		</function>
		
		<function name="aero/force/Drag_slat_L">
			<description>Drag due to slat L</description>
			<product>
				<property>aero/qbar-psf</property>
				<property>metrics/Sw-sqft</property>
				<property>fcs/slat-L-deg</property>
				<value>0.00451</value>
			</product>
		</function>
		
		<function name="aero/force/Drag_slat_R">
			<description>Drag due to slat R</description>
			<product>
				<property>aero/qbar-psf</property>
				<property>metrics/Sw-sqft</property>
				<property>fcs/slat-R-deg</property>
				<value>0.00451</value>
			</product>
		</function>
		
		<function name="aero/force/Drag_gear">
			<description>Drag due to gear</description>
			<product>
				<property>aero/qbar-psf</property>
				<property>metrics/Sw-sqft</property>
				<property>gear/gear-pos-norm</property>
				<value>0.01846</value>
			</product>
		</function>
		
		<function name="aero/force/Drag_speedbrake">
			<description>Drag due to speedbrakes</description>
			<product>
				<property>aero/qbar-psf</property>
				<property>metrics/Sw-sqft</property>
				<property>fcs/airbrake-deg</property>
				<value>0.00106</value>
			</product>
		</function>
	
	</axis>
	
	<axis name="SIDE">
		
		<function name="aero/force/Side_beta">
			<description>Side force due to beta</description>
			<product>
				<property>aero/qbar-psf</property>
				<property>metrics/Sw-sqft</property>
				<property>aero/beta-rad</property>
				<value>-0.9765</value>
			</product>
		</function>
		
		<function name="aero/force/Side_roll_rate">
			<description>Side force due to roll rate</description>
			<product>
				<property>aero/qbar-psf</property>
				<property>metrics/Sw-sqft</property>
				<property>aero/bi2vel</property>
				<property>velocities/p-aero-rad_sec</property>
				<table>
					<independentVar lookup="row">aero/Re</independentVar>
					<tableData>
						103071296  0.2160
						113378416  0.0159
						154606944  0.0069
						206465920  0.0071
					</tableData>
				</table>
			</product>
		</function>
		
		<function name="aero/force/Side_yaw_rate">
			<description>Side force due to yaw rate</description>
			<product>
				<property>aero/qbar-psf</property>
				<property>metrics/Sw-sqft</property>
				<property>aero/bi2vel</property>
				<property>velocities/r-aero-rad_sec</property>
				<value>1.246</value>
			</product>
		</function>
		
		<function name="aero/force/Side_rudder">
			<description>Side force due to rudder</description>
			<product>
				<property>aero/qbar-psf</property>
				<property>metrics/Sw-sqft</property>
				<toradians><property>fcs/rudder-deg</property></toradians>
				<value>0.298</value>
			</product>
		</function>
	
	</axis>
	
	<axis name="PITCH">
		
		<function name="aero/moment/Pitch_alpha">
			<description>Pitching moment due to alpha</description>
			<product>
				<property>aero/qbar-psf</property>
				<property>metrics/Sw-sqft</property>
				<property>metrics/cbarw-ft</property>
				<table>
					<independentVar lookup="row">aero/alpha-deg</independentVar>
					<tableData>
						-30 -0.00106
						-15 -0.00051
						  0  0.00002
						 15  0.00062
						 30  0.00131
					</tableData>
				</table>
			</product>
		</function>
		
		<function name="aero/moment/Pitch_foreplane_L">
			<description>Pitch moment due to foreplane L</description>
			<product>
				<property>aero/qbar-psf</property>
				<property>metrics/Sw-sqft</property>
				<property>metrics/cbarw-ft</property>
				<toradians><property>fcs/foreplane-L-deg</property></toradians>
				<value>-0.5133</value>
			</product>
		</function>
		
		<function name="aero/moment/Pitch_foreplane_R">
			<description>Pitch moment due to foreplane R</description>
			<product>
				<property>aero/qbar-psf</property>
				<property>metrics/Sw-sqft</property>
				<property>metrics/cbarw-ft</property>
				<toradians><property>fcs/foreplane-R-deg</property></toradians>
				<value>-0.5133</value>
			</product>
		</function>
		
		<function name="aero/moment/Pitch_elevon_1L">
			<description>Pitch moment due to elevon 1L</description>
			<product>
				<property>aero/qbar-psf</property>
				<property>metrics/Sw-sqft</property>
				<property>metrics/cbarw-ft</property>
				<toradians><property>fcs/elevon-1L-deg</property></toradians>
				<value>-0.5033</value>
			</product>
		</function>
		
		<function name="aero/moment/Pitch_elevon_2L">
			<description>Pitch moment due to elevon 2L</description>
			<product>
				<property>aero/qbar-psf</property>
				<property>metrics/Sw-sqft</property>
				<property>metrics/cbarw-ft</property>
				<toradians><property>fcs/elevon-2L-deg</property></toradians>
				<value>0.5233</value>
			</product>
		</function>
		
		<function name="aero/moment/Pitch_elevon_2R">
			<description>Pitch moment due to elevon 2R</description>
			<product>
				<property>aero/qbar-psf</property>
				<property>metrics/Sw-sqft</property>
				<property>metrics/cbarw-ft</property>
				<toradians><property>fcs/elevon-2R-deg</property></toradians>
				<value>0.5233</value>
			</product>
		</function>
		
		<function name="aero/moment/Pitch_elevon_1R">
			<description>Pitch moment due to elevon 1R</description>
			<product>
				<property>aero/qbar-psf</property>
				<property>metrics/Sw-sqft</property>
				<property>metrics/cbarw-ft</property>
				<toradians><property>fcs/elevon-1R-deg</property></toradians>
				<value>-0.5033</value>
			</product>
		</function>
		
		<function name="aero/moment/Pitch_damp">
			<description>Pitch moment due to pitch rate</description>
			<product>
				<property>aero/qbar-psf</property>
				<property>metrics/Sw-sqft</property>
				<property>metrics/cbarw-ft</property>
				<property>aero/ci2vel</property>
				<property>velocities/q-aero-rad_sec</property>
				<value>-9.3931</value>
			</product>
		</function>
		
		<function name="aero/moment/Pitch_alphadot">
			<description>Pitch moment due to alpha rate</description>
			<product>
				<property>aero/qbar-psf</property>
				<property>metrics/Sw-sqft</property>
				<property>metrics/cbarw-ft</property>
				<property>aero/ci2vel</property>
				<property>aero/alphadot-rad_sec</property>
				<value>-9.4976</value>
			</product>
		</function>
	
	</axis>
	
	<axis name="ROLL">
		
		<function name="aero/moment/Roll_beta">
			<description>Roll moment due to beta</description>
			<product>
				<property>aero/qbar-psf</property>
				<property>metrics/Sw-sqft</property>
				<property>metrics/bw-ft</property>
				<property>aero/beta-rad</property>
				<value>-0.0217</value>
			</product>
		</function>
		
		<function name="aero/moment/Roll_damp">
			<description>Roll moment due to roll rate</description>
			<product>
				<property>aero/qbar-psf</property>
				<property>metrics/Sw-sqft</property>
				<property>metrics/bw-ft</property>
				<property>aero/bi2vel</property>
				<property>velocities/p-aero-rad_sec</property>
				<value>-0.397</value>
			</product>
		</function>
		
		<function name="aero/moment/Roll_yaw">
			<description>Roll moment due to yaw rate</description>
			<product>
				<property>aero/qbar-psf</property>
				<property>metrics/Sw-sqft</property>
				<property>metrics/bw-ft</property>
				<property>aero/bi2vel</property>
				<property>velocities/r-aero-rad_sec</property>
				<value>0.0876</value>
			</product>
		</function>
		
		<function name="aero/moment/Roll_elevon_1L">
			<description>Roll moment due to elevon 1L</description>
			<product>
				<property>aero/qbar-psf</property>
				<property>metrics/Sw-sqft</property>
				<property>metrics/bw-ft</property>
				<toradians><property>fcs/elevon-1L-deg</property></toradians>
				<value>0.0495</value>
			</product>
		</function>
		
		<function name="aero/moment/Roll_elevon_2L">
			<description>Roll moment due to elevon 2L</description>
			<product>
				<property>aero/qbar-psf</property>
				<property>metrics/Sw-sqft</property>
				<property>metrics/bw-ft</property>
				<toradians><property>fcs/elevon-2L-deg</property></toradians>
				<value>0.0595</value>
			</product>
		</function>
		
		<function name="aero/moment/Roll_elevon_2R">
			<description>Roll moment due to elevon 2R</description>
			<product>
				<property>aero/qbar-psf</property>
				<property>metrics/Sw-sqft</property>
				<property>metrics/bw-ft</property>
				<toradians><property>fcs/elevon-2R-deg</property></toradians>
				<value>-0.0595</value>
			</product>
		</function>
		
		<function name="aero/moment/Roll_elevon_1R">
			<description>Roll moment due to elevon 1R</description>
			<product>
				<property>aero/qbar-psf</property>
				<property>metrics/Sw-sqft</property>
				<property>metrics/bw-ft</property>
				<toradians><property>fcs/elevon-1R-deg</property></toradians>
				<value>-0.0495</value>
			</product>
		</function>
		
		<function name="aero/moment/Roll_rudder">
			<description>Roll moment due to rudder</description>
			<product>
				<property>aero/qbar-psf</property>
				<property>metrics/Sw-sqft</property>
				<property>metrics/bw-ft</property>
				<toradians><property>fcs/rudder-deg</property></toradians>
				<value>0.0317</value>
			</product>
		</function>
	
	</axis>
	
	<axis name="YAW">
		
		<function name="aero/moment/Yaw_beta">
			<description>Yaw moment due to beta</description>
			<product>
				<property>aero/qbar-psf</property>
				<property>metrics/Sw-sqft</property>
				<property>metrics/bw-ft</property>
				<property>aero/beta-rad</property>
				<value>0.05896</value>
			</product>
		</function>
		
		<function name="aero/moment/Yaw_roll_rate">
			<description>Yaw moment due to roll rate</description>
			<product>
				<property>aero/qbar-psf</property>
				<property>metrics/Sw-sqft</property>
				<property>metrics/bw-ft</property>
				<property>aero/bi2vel</property>
				<property>velocities/p-rad_sec</property>
				<table>
					<independentVar lookup="row">aero/Re</independentVar>
					<tableData>
						17307328 -0.0749
						19038060 -0.0045
						25960990 -0.0016
						34828468 -0.0009
					</tableData>
				</table>
			</product>
		</function>
		
		<function name="aero/moment/Yaw_damp">
			<description>Yaw moment due to yaw rate</description>
			<product>
				<property>aero/qbar-psf</property>
				<property>metrics/Sw-sqft</property>
				<property>metrics/bw-ft</property>
				<property>aero/bi2vel</property>
				<property>velocities/r-aero-rad_sec</property>
				<value>-0.356</value>
			</product>
		</function>
		
		<function name="aero/moment/Yaw_rudder">
			<description>Yaw moment due to rudder</description>
			<product>
				<property>aero/qbar-psf</property>
				<property>metrics/Sw-sqft</property>
				<property>metrics/bw-ft</property>
				<toradians><property>fcs/rudder-deg</property></toradians>
				<value>0.0594</value>
			</product>
		</function>
	
	</axis>

</aerodynamics>
